{"stats":{"minecraft:killed":{"undead_revamp2:clogger":1,"undead_revamp2:deadclogger":1,"minecraft:zombie":26},"minecraft:custom":{"lootr:looted_stat":9,"minecraft:mob_kills":28,"minecraft:interact_with_anvil":4,"minecraft:interact_with_crafting_table":37,"minecraft:interact_with_campfire":8,"minecraft:damage_dealt_resisted":343,"minecraft:leave_game":9,"minecraft:time_since_death":8002,"minecraft:climb_one_cm":11960,"minecraft:sprint_one_cm":405865,"minecraft:walk_one_cm":1041900,"minecraft:drop":55,"minecraft:damage_dealt_absorbed":17,"minecraft:play_time":265255,"minecraft:deaths":23,"minecraft:sneak_time":3762,"minecraft:walk_under_water_one_cm":11176,"minecraft:jump":3357,"minecraft:walk_on_water_one_cm":6186,"minecraft:total_world_time":265927,"minecraft:interact_with_furnace":18,"minecraft:sleep_in_bed":7,"minecraft:time_since_rest":1069,"minecraft:damage_taken":6164,"minecraft:damage_dealt":7119,"minecraft:swim_one_cm":1455,"minecraft:fly_one_cm":542713,"minecraft:open_chest":100,"minecraft:crouch_one_cm":8319,"waystones:waystone_activated":1,"minecraft:fall_one_cm":64577},"minecraft:used":{"zombie_extreme:butcher_knife":110,"apocalypsenow:swatriotcontrol_leggings":1,"apocalypsenow:royal_canada_police_officer_chestplate":1,"minecraft:stone_shovel":84,"minecraft:chest":14,"tacz:gun_smith_table":5,"extinction:corpse":1,"minecraft:decorated_pot":1,"minecraft:stone_hoe":29,"minecraft:torch":35,"minecraft:dirt":55,"minecraft:cobblestone_wall":1,"minecraft:carrot":2,"minecraft:acacia_sapling":1,"minecraft:acacia_button":1,"minecraft:granite":1,"minecraft:azure_bluet":7,"apocalypsenow:red_football_armor_chestplate":1,"minecraft:dark_oak_planks":3,"farmersdelight:tomato":3,"zombie_extreme:dog_food":1,"minecraft:acacia_slab":202,"better_mob_food:cooked_flesh":4,"minecraft:furnace":1,"zombie_extreme:soda":2,"minecraft:egg":2,"minecraft:potato":1,"minecraft:acacia_planks":3,"minecraft:orange_terracotta":1,"minecraft:wheat_seeds":17,"minecraft:mossy_stone_bricks":1,"farmersdelight:iron_knife":4,"minecraft:water_bucket":7,"minecraft:glass_bottle":22,"minecraft:stone_pickaxe":176,"pointblank:printer":1,"minecraft:wooden_pickaxe":7,"minecraft:sugar_cane":6,"zombie_extreme:chips":1,"minecraft:cookie":1,"minecraft:yellow_terracotta":1,"zombie_extreme:golf_club":66,"minecraft:red_bed":5,"minecraft:crafting_table":8,"minecraft:light_gray_terracotta":25,"minecraft:campfire":2,"minecraft:melon_slice":4,"minecraft:bread":3,"apocalypsenow:saw_pole":2,"minecraft:stone_axe":106,"minecraft:potion":40,"minecraft:wooden_sword":47,"minecraft:cobblestone":34,"minecraft:andesite":42,"minecraft:bucket":8,"minecraft:coarse_dirt":6,"minecraft:dandelion":1,"minecraft:cobweb":1,"minecraft:experience_bottle":7,"minecraft:chainmail_leggings":1},"minecraft:killed_by":{"minecraft:zombie":7},"minecraft:broken":{"apocalypsenow:contamination_suit_white_boots":1,"minecraft:iron_chestplate":1,"apocalypsenow:usa_armor_boots":1,"minecraft:stone_pickaxe":1,"minecraft:wooden_sword":1,"minecraft:leather_boots":1},"minecraft:mined":{"minecraft:dark_oak_log":1,"minecraft:glow_lichen":1,"minecraft:granite":1,"minecraft:acacia_log":54,"minecraft:grass_block":55,"minecraft:decorated_pot":1,"extinction:corpse":1,"minecraft:acacia_slab":10,"minecraft:black_stained_glass_pane":2,"minecraft:carrots":5,"minecraft:iron_ore":4,"minecraft:andesite":2,"minecraft:azure_bluet":4,"minecraft:vine":19,"minecraft:stone":66,"minecraft:white_wool":7,"immersiveengineering:ore_aluminum":11,"lootr:lootr_chest":1,"minecraft:red_bed":5,"farmersdelight:organic_compost":5,"minecraft:dandelion":8,"minecraft:crafting_table":3,"minecraft:torch":14,"minecraft:light_gray_terracotta":25,"minecraft:melon":1,"minecraft:chest":8,"minecraft:tall_grass":30,"minecraft:copper_ore":35,"minecraft:cobblestone":19,"farmersdelight:wild_tomatoes":7,"minecraft:sugar_cane":6,"minecraft:oak_planks":1,"minecraft:wall_torch":14,"minecraft:birch_planks":1,"minecraft:coarse_dirt":6,"minecraft:cobblestone_wall":2,"minecraft:wheat":8,"minecraft:spruce_log":5,"minecraft:grass":114,"minecraft:coal_ore":14,"minecraft:gravel":31,"minecraft:dirt":12,"minecraft:cobweb":51,"minecraft:acacia_planks":1},"minecraft:crafted":{"minecraft:wooden_sword":2,"minecraft:stone_shovel":1,"minecraft:furnace":1,"minecraft:bone_meal":3,"minecraft:stone_pickaxe":1,"minecraft:chest":4,"minecraft:dark_oak_planks":1,"minecraft:stone_hoe":1,"minecraft:crafting_table":5,"minecraft:spruce_planks":5,"minecraft:acacia_slab":32,"minecraft:wooden_pickaxe":1,"minecraft:bucket":2,"minecraft:acacia_button":1,"minecraft:campfire":2,"minecraft:stone_axe":1,"minecraft:air":454,"minecraft:stick":15,"minecraft:iron_ingot":4,"minecraft:acacia_planks":54,"minecraft:torch":3},"minecraft:picked_up":{"minecraft:crafting_table":4,"minecraft:iron_chestplate":1,"minecraft:coarse_dirt":6,"minecraft:wheat":20,"minecraft:azure_bluet":7,"minecraft:diamond_sword":1,"minecraft:wooden_pickaxe":1,"minecraft:potion":4,"minecraft:red_bed":5,"minecraft:string":50,"minecraft:raw_copper":131,"apocalypsenow:red_football_armor_chestplate":2,"apocalypsenow:emergency_axe":1,"extinction:rubber_sheet":1,"minecraft:melon_slice":4,"minecraft:sugar_cane":10,"minecraft:chest":8,"apocalypsenow:gardening_scissors":1,"minecraft:egg":2,"pointblank:gunmetal_ingot":2,"minecraft:stick":6,"minecraft:raw_iron":4,"apocalypsenow:head_cutter":1,"zombie_extreme:soda_used":1,"minecraft:torch":27,"minecraft:acacia_log":54,"minecraft:porkchop":3,"pointblank:gunmetal_nugget":52,"farmersdelight:tomato_seeds":7,"apocalypsenow:hammer":2,"minecraft:carrot":18,"apocalypsenow:black_football_armor_chestplate":1,"undead_revamp2:cloogerribs":38,"minecraft:rotten_flesh":78,"minecraft:decorated_pot":1,"apocalypsenow:scrapmetal":1,"minecraft:yellow_terracotta":2,"zombie_extreme:butcher_knife":1,"minecraft:white_wool":7,"minecraft:cobblestone":86,"undead_revamp2:cloggerupgrade":1,"zombie_extreme:pipe":1,"minecraft:andesite":65,"minecraft:flint":4,"minecraft:cobblestone_wall":2,"apocalypsenow:usa_armor_boots":2,"farmersdelight:tomato":3,"minecraft:dirt":114,"minecraft:orange_terracotta":5,"farmersdelight:organic_compost":5,"minecraft:bone":26,"farmersdelight:iron_knife":2,"minecraft:acacia_planks":33,"minecraft:gray_terracotta":14,"apocalypsenow:human_flesh":22,"minecraft:wheat_seeds":75,"better_mob_food:cooked_flesh":9,"apocalypsenow:royal_canada_police_officer_chestplate":1,"minecraft:stone_pickaxe":1,"minecraft:iron_ingot":129,"minecraft:mossy_stone_bricks":1,"minecraft:acacia_sapling":7,"apocalypsenow:cooked_cockroach":1,"extinction:corpse":1,"apocalypsenow:contamination_suit_white_boots":1,"apocalypsenow:saw_pole":1,"apocalypsenow:swatriotcontrol_leggings":1,"minecraft:dandelion":11,"apocalypsenow:bushcraft_axe":1,"minecraft:gravel":27,"refinedstorage:quartz_enriched_iron":119,"immersiveengineering:raw_aluminum":11,"sophisticatedbackpacks:iron_backpack":1,"minecraft:spruce_log":5,"minecraft:dark_oak_log":1,"apocalypsenow:military_riot_armor_leggings":1,"minecraft:light_gray_terracotta":25,"minecraft:slime_ball":11,"minecraft:diamond":6,"immersiveengineering:seed":27,"minecraft:stone_axe":1,"minecraft:granite":1,"apocalypsenow:usa_armor_helmet":1,"minecraft:acacia_slab":10,"apocalypsenow:helicopter_helmet":1,"minecraft:coal":14},"minecraft:dropped":{"sophisticatedbackpacks:iron_backpack":1,"farmersdelight:iron_knife":2,"minecraft:iron_ingot":255,"minecraft:wheat_seeds":6,"minecraft:glass_bottle":5,"minecraft:diamond":58,"minecraft:yellow_terracotta":1,"minecraft:dirt":1,"zombie_extreme:soda_used":1,"apocalypsenow:saw_pole":1,"pointblank:guninternals":3,"minecraft:potion":2,"extinction:rubber_sheet":1,"minecraft:white_wool":1,"minecraft:acacia_planks":32,"apocalypsenow:canned_fish":1,"minecraft:stone_axe":1,"apocalypsenow:hammer":2,"refinedstorage:quartz_enriched_iron":128,"apocalypsenow:scrapmetal":1,"minecraft:cobblestone_wall":1,"minecraft:wheat":3,"minecraft:rotten_flesh":2,"apocalypsenow:bushcraft_axe":1,"apocalypsenow:head_cutter":1,"minecraft:diamond_sword":1,"apocalypsenow:gardening_scissors":1,"zombie_extreme:butcher_knife":1,"better_mob_food:cooked_flesh":1,"minecraft:wooden_pickaxe":1,"apocalypsenow:emergency_axe":1,"immersiveengineering:seed":3}},"DataVersion":3465}